flask_fast_cache/__init__.py
flask_fast_cache-0.0.1.dev1.dist-info/METADATA
flask_fast_cache-0.0.1.dev1.dist-info/RECORD
flask_fast_cache-0.0.1.dev1.dist-info/WHEEL
flask_fast_cache-0.0.1.dev1.dist-info/top_level.txt
